[{"line":5,"elements":[{"start_timestamp":"2023-04-10T21:01:11.822Z","line":8,"name":"Validar que as especificações do produto de acordo com as informações retornadas do banco de automação","description":"","id":"remover-produto-do-carrinho-de-compras;validar-que-as-especificações-do-produto-de-acordo-com-as-informações-retornadas-do-banco-de-automação","type":"scenario","keyword":"Cenário","steps":[{"result":{"duration":2817000000,"status":"passed"},"line":9,"name":"que eu esteja na página inicial do site","match":{"location":"steps.StepCenario.Login()"},"keyword":"Dado "},{"result":{"duration":17000000,"status":"passed"},"line":10,"name":"clicar na opcao Special Offer","match":{"location":"steps.StepCenario.click_SpecialOffer()"},"keyword":"E "},{"result":{"duration":22000000,"status":"passed"},"line":11,"name":"clicar no botao See Offer","match":{"location":"steps.StepCenario.click_SeeOffer()"},"keyword":"E "},{"result":{"duration":10020000000,"status":"passed"},"line":12,"name":"cliquei no botão Add to cart","match":{"location":"steps.StepCenario.click_AddToCart()"},"keyword":"E "},{"result":{"duration":69000000,"status":"passed"},"line":13,"name":"clicar no carrinho de compras","match":{"location":"steps.StepCenario.clicarCarrinho()"},"keyword":"Quando "},{"result":{"duration":22000000,"status":"passed"},"line":14,"name":"remover o produto do carrinho de compras","match":{"location":"steps.StepCenario.removerCompra()"},"keyword":"E "},{"result":{"duration":705000000,"status":"passed"},"line":15,"name":"valido que o carrinho de compras está vazio","match":{"location":"steps.StepCenario.verificarCarrinhoVazio()"},"keyword":"Entao "}],"tags":[{"name":"@CT001_ValidacaoEspecificacoes"},{"name":"@Geral"}]}],"name":"Remover produto do carrinho de compras","description":"","id":"remover-produto-do-carrinho-de-compras","keyword":"Funcionalidade","uri":"file:src/test/resources/features/cenario1.feature","tags":[]}]